Metadata-Version: 1.0
Name: pycopy-serial
Version: 0.4
Summary: pySerial-like module for Pycopy unix port (https://github.com/pfalcon/pycopy).
Home-page: https://github.com/pfalcon/pycopy-serial
Author: Paul Sokolovsky
Author-email: pfalcon@users.sourceforge.net
License: MIT
Platform: UNKNOWN
